baslertwo/__init__.py
baslertwo/__main__.py
baslertwo/py.typed
basler2-0.1.0a0.dist-info/entry_points.txt
basler2-0.1.0a0.dist-info/LICENSE.rst
basler2-0.1.0a0.dist-info/WHEEL
basler2-0.1.0a0.dist-info/METADATA
basler2-0.1.0a0.dist-info/RECORD
