Metadata-Version: 2.1
Name: basler2
Version: 0.1.0a0
Summary: BaslerTwo
Home-page: https://github.com/stopmosk/basler2
License: MIT
Author: Sergei Shutov
Author-email: serg.shutov@gmail.com
Requires-Python: >=3.7,<4.0
Classifier: Development Status :: 1 - Planning
Classifier: License :: OSI Approved :: MIT License
Classifier: Programming Language :: Python :: 3
Classifier: Programming Language :: Python :: 3.10
Classifier: Programming Language :: Python :: 3.7
Classifier: Programming Language :: Python :: 3.8
Classifier: Programming Language :: Python :: 3.9
Requires-Dist: click (>=8.0.1,<9.0.0)
Project-URL: Changelog, https://github.com/stopmosk/basler2/releases
Project-URL: Documentation, https://basler2.readthedocs.io
Project-URL: Repository, https://github.com/stopmosk/basler2
